{
    "Maxwell": {
        "checkpoints": [
            {
                "steps": 499964,
                "file_path": "results\\run2_3\\Maxwell\\Maxwell-499964.onnx",
                "reward": 6.0232228543521105,
                "creation_time": 1715985544.3054783,
                "auxillary_file_paths": [
                    "results\\run2_3\\Maxwell\\Maxwell-499964.pt"
                ]
            },
            {
                "steps": 999989,
                "file_path": "results\\run2_3\\Maxwell\\Maxwell-999989.onnx",
                "reward": 7.325984397272426,
                "creation_time": 1715989144.3495188,
                "auxillary_file_paths": [
                    "results\\run2_3\\Maxwell\\Maxwell-999989.pt"
                ]
            },
            {
                "steps": 1000078,
                "file_path": "results\\run2_3\\Maxwell\\Maxwell-1000078.onnx",
                "reward": 7.367187654599547,
                "creation_time": 1715989144.4360218,
                "auxillary_file_paths": [
                    "results\\run2_3\\Maxwell\\Maxwell-1000078.pt"
                ]
            }
        ],
        "final_checkpoint": {
            "steps": 1000078,
            "file_path": "results\\run2_3\\Maxwell.onnx",
            "reward": 7.367187654599547,
            "creation_time": 1715989144.4360218,
            "auxillary_file_paths": [
                "results\\run2_3\\Maxwell\\Maxwell-1000078.pt"
            ]
        }
    },
    "metadata": {
        "stats_format_version": "0.3.0",
        "mlagents_version": "0.28.0",
        "torch_version": "1.7.1+cu110"
    }
}